mapchiral/__init__.py
mapchiral/mapchiral.py
mapchiral-0.0.7.dist-info/LICENSE
mapchiral-0.0.7.dist-info/METADATA
mapchiral-0.0.7.dist-info/WHEEL
mapchiral-0.0.7.dist-info/top_level.txt
mapchiral-0.0.7.dist-info/RECORD
