Metadata-Version: 2.1
Name: mapchiral
Version: 0.0.7
Summary: Chiral MinHashed Atom-Pair Fingerprint  (MAP4C) 
Author: Markus Orsi
Author-email: <markus.orsi@unibe.ch>
Keywords: cheminformatics,mapchiral,fingerprint
Classifier: Development Status :: 3 - Alpha
Classifier: Intended Audience :: Education
Classifier: Programming Language :: Python :: 3
Classifier: Operating System :: MacOS :: MacOS X
Classifier: Operating System :: Microsoft :: Windows
License-File: LICENSE
